diagram_detector/__init__.py
diagram_detector/cache.py
diagram_detector/cli.py
diagram_detector/detector.py
diagram_detector/models.py
diagram_detector/py.typed
diagram_detector/remote_pdf.py
diagram_detector/remote_ssh.py
diagram_detector/utils.py
diagram_detector-1.1.0.dist-info/licenses/LICENSE
diagram_detector-1.1.0.dist-info/METADATA
diagram_detector-1.1.0.dist-info/WHEEL
diagram_detector-1.1.0.dist-info/entry_points.txt
diagram_detector-1.1.0.dist-info/top_level.txt
diagram_detector-1.1.0.dist-info/RECORD
