Metadata-Version: 2.4
Name: diagram-detector
Version: 1.1.0
Summary: Production-ready diagram detection for academic papers using YOLO11
Author-email: Henrik Kragh Sørensen <hks@ku.dk>
Maintainer-email: Henrik Kragh Sørensen <hks@ku.dk>
License: MIT
Project-URL: Homepage, https://github.com/hksorensen/diagram-detector
Project-URL: Documentation, https://diagram-detector.readthedocs.io
Project-URL: Repository, https://github.com/hksorensen/diagram-detector
Project-URL: Issues, https://github.com/hksorensen/diagram-detector/issues
Project-URL: Changelog, https://github.com/hksorensen/diagram-detector/blob/main/CHANGELOG.md
Keywords: diagram,detection,yolo,computer-vision,academic-papers,pdf,machine-learning
Classifier: Development Status :: 4 - Beta
Classifier: Intended Audience :: Science/Research
Classifier: License :: OSI Approved :: MIT License
Classifier: Programming Language :: Python :: 3
Classifier: Programming Language :: Python :: 3.9
Classifier: Programming Language :: Python :: 3.10
Classifier: Programming Language :: Python :: 3.11
Classifier: Programming Language :: Python :: 3.12
Classifier: Topic :: Scientific/Engineering :: Artificial Intelligence
Classifier: Topic :: Scientific/Engineering :: Image Recognition
Requires-Python: >=3.9
License-File: LICENSE
Requires-Dist: ultralytics>=8.0.0
Requires-Dist: torch>=2.0.0
Requires-Dist: torchvision>=0.15.0
Requires-Dist: opencv-python-headless>=4.8.0
Requires-Dist: pillow>=10.0.0
Requires-Dist: numpy>=1.24.0
Requires-Dist: tqdm>=4.65.0
Requires-Dist: pyyaml>=6.0
Requires-Dist: pdf2image>=1.16.0
Requires-Dist: huggingface_hub>=0.19.0
Provides-Extra: dev
Requires-Dist: pytest>=7.4.0; extra == "dev"
Requires-Dist: pytest-cov>=4.1.0; extra == "dev"
Requires-Dist: black>=23.7.0; extra == "dev"
Requires-Dist: flake8>=6.0.0; extra == "dev"
Requires-Dist: mypy>=1.4.0; extra == "dev"
Requires-Dist: isort>=5.12.0; extra == "dev"
Provides-Extra: onnx
Requires-Dist: onnxruntime>=1.15.0; extra == "onnx"
Provides-Extra: gpu
Requires-Dist: onnxruntime-gpu>=1.15.0; extra == "gpu"
Dynamic: license-file
